.dockerignore
.flake8
.gitignore
.travis.yml
CONTRIBUTING.md
Dockerfile
LICENSE
MANIFEST.in
README.pypi.rst
README.rst
README.txt
STYLE.md
configtest_dev.py
constraints.txt
constraints.txt.default
convert_error_code.py
dev-requirements.txt
dev_glue.py
ez_setup.py
readthedocs.yml
repo_dev.py
requirements.txt
server_dev.py
setup.py
deploy/001-ga4gh.conf
deploy/application.wsgi
deploy/config.py
docs/Makefile
docs/conf.py
docs/configuration.rst
docs/datarepo.rst
docs/demo.rst
docs/development.rst
docs/environment.yml
docs/index.rst
docs/installation.rst
docs/introduction.rst
docs/ref_server_profiling.rst
docs/status.rst
docs/_static/logo_ga.png
docs/images/Consent_screen_-_ga4gh.png
docs/images/Create_project.png
docs/images/Credentials_-_ga4gh.png
docs/images/Credentials_-_ga4gh_2.png
docs/images/Credentials_-_ga4gh_3.png
docs/images/auth0-create-api.png
docs/images/auth0-create-client-details-callback.PNG
docs/images/auth0-create-client-details.png
docs/images/auth0-create-client.png
docs/images/auth0-create-user.png
docs/images/auth0-database-details.png
docs/images/auth0-ga4gh-api-details.png
docs/images/auth0-ga4gh-scopes.png
docs/images/auth0-new-database.png
docs/images/auth0-testing.PNG
docs/images/auth0-token.png
ga4gh/__init__.py
ga4gh/server/__init__.py
ga4gh/server/_version.py
ga4gh/server/backend.py
ga4gh/server/configtest.py
ga4gh/server/datarepo.py
ga4gh/server/exceptions.py
ga4gh/server/frontend.py
ga4gh/server/gff3.py
ga4gh/server/paging.py
ga4gh/server/response_builder.py
ga4gh/server/serverconfig.py
ga4gh/server/sqlite_backend.py
ga4gh/server/stuff.cfg
ga4gh/server/auth/__init__.py
ga4gh/server/cli/__init__.py
ga4gh/server/cli/configtest.py
ga4gh/server/cli/repomanager.py
ga4gh/server/cli/server.py
ga4gh/server/datamodel/__init__.py
ga4gh/server/datamodel/bio_metadata.py
ga4gh/server/datamodel/continuous.py
ga4gh/server/datamodel/datasets.py
ga4gh/server/datamodel/genotype_phenotype.py
ga4gh/server/datamodel/genotype_phenotype_featureset.py
ga4gh_server.egg-info/PKG-INFO
ga4gh_server.egg-info/SOURCES.txt
ga4gh_server.egg-info/dependency_links.txt
ga4gh_server.egg-info/entry_points.txt
ga4gh_server.egg-info/namespace_packages.txt
ga4gh_server.egg-info/not-zip-safe
ga4gh_server.egg-info/requires.txt
ga4gh_server.egg-info/top_level.txt
