Metadata-Version: 1.1
Name: ga4gh-server
Version: 0.3.6
Summary: A reference implementation of the GA4GH API
Home-page: https://github.com/ga4gh/ga4gh-server
Author: Global Alliance for Genomics and Health
Author-email: theglobalalliance@genomicsandhealth.org
License: Apache License 2.0
Keywords: genomics,reference
Platform: UNKNOWN
Classifier: Development Status :: 3 - Alpha
Classifier: Intended Audience :: Science/Research
Classifier: License :: OSI Approved :: Apache Software License
Classifier: Natural Language :: English
Classifier: Programming Language :: Python :: 2.7
Classifier: Topic :: Scientific/Engineering :: Bio-Informatics
